fluxwallet/__init__.py
fluxwallet/blocks.py
fluxwallet/config/VERSION
fluxwallet/config/__init__.py
fluxwallet/config/config.py
fluxwallet/config/opcodes.py
fluxwallet/config/secp256k1.py
fluxwallet/data/config.ini
fluxwallet/data/config.ini.unittest
fluxwallet/data/networks.json
fluxwallet/data/providers.examples.json
fluxwallet/data/providers.json
fluxwallet/data/providers.old.json
fluxwallet/db.py
fluxwallet/db_cache.py
fluxwallet/db_new.py
fluxwallet/encoding.py
fluxwallet/flux_transaction.py
fluxwallet/keys.py
fluxwallet/main.py
fluxwallet/mnemonic.py
fluxwallet/networks.py
fluxwallet/pyproject.toml
fluxwallet/scripts.py
fluxwallet/services/__init__.py
fluxwallet/services/authproxy.py
fluxwallet/services/baseclient.py
fluxwallet/services/bcoin.py
fluxwallet/services/bitaps.py
fluxwallet/services/bitcoind.py
fluxwallet/services/bitcoinlibtest.py
fluxwallet/services/bitflyer.py
fluxwallet/services/bitgo.py
fluxwallet/services/blockchaininfo.py
fluxwallet/services/blockchair.py
fluxwallet/services/blockcypher.py
fluxwallet/services/blocksmurfer.py
fluxwallet/services/blockstream.py
fluxwallet/services/chainso.py
fluxwallet/services/cryptoid.py
fluxwallet/services/dashd.py
fluxwallet/services/dogecoind.py
fluxwallet/services/insightdash.py
fluxwallet/services/litecoinblockexplorer.py
fluxwallet/services/litecoind.py
fluxwallet/services/litecoreio.py
fluxwallet/services/mempool.py
fluxwallet/services/runonflux.py
fluxwallet/services/services.py
fluxwallet/tools/__init__.py
fluxwallet/tools/clw.py
fluxwallet/tools/mnemonic_key_create.py
fluxwallet/tools/sign_raw.py
fluxwallet/tools/wallet_multisig_2of3.py
fluxwallet/transactions.py
fluxwallet/values.py
fluxwallet/wallet/__init__.py
fluxwallet/wallet/errors.py
fluxwallet/wallet/helpers.py
fluxwallet/wallet/wallet.py
fluxwallet/wallet/wallet_key.py
fluxwallet/wallet/wallet_transaction.py
fluxwallet/wallet/wallet_transaction_old.py
fluxwallet/wallets.py
fluxwallet/wallets_new.py
fluxwallet-0.2.3.dist-info/LICENSE
fluxwallet-0.2.3.dist-info/METADATA
fluxwallet-0.2.3.dist-info/WHEEL
fluxwallet-0.2.3.dist-info/RECORD
